magicclass/__init__.py
magicclass/_app.py
magicclass/_compat.py
magicclass/_exceptions.py
magicclass/_register_types.py
magicclass/command_palette.py
magicclass/core.py
magicclass/help.py
magicclass/plot_api.py
magicclass/serialize.py
magicclass/signature.py
magicclass/undo.py
magicclass/_gui/__init__.py
magicclass/_gui/_base.py
magicclass/_gui/_dock_widget.py
magicclass/_gui/_function_gui.py
magicclass/_gui/_gui_modes.py
magicclass/_gui/_icon.py
magicclass/_gui/_macro.py
magicclass/_gui/_macro_utils.py
magicclass/_gui/_message_box.py
magicclass/_gui/_napari_type.py
magicclass/_gui/class_gui.py
magicclass/_gui/keybinding.py
magicclass/_gui/menu_gui.py
magicclass/_gui/mgui_ext.py
magicclass/_gui/runner.py
magicclass/_gui/toolbar.py
magicclass/_gui/utils.py
magicclass/box/__init__.py
magicclass/box/_fields.py
magicclass/ext/__init__.py
magicclass/ext/_colors.py
magicclass/ext/_doc.py
magicclass/ext/_shared_utils.py
magicclass/ext/dask/__init__.py
magicclass/ext/dask/progress.py
magicclass/ext/dask/resource.py
magicclass/ext/napari/__init__.py
magicclass/ext/napari/_magicgui.py
magicclass/ext/napari/types.py
magicclass/ext/napari/utils.py
magicclass/ext/napari/viewer.py
magicclass/ext/napari/widgets.py
magicclass/ext/pandas/__init__.py
magicclass/ext/pandas/_viewer.py
magicclass/ext/pandas/tests/__init__.py
magicclass/ext/pandas/tests/test_viewer.py
magicclass/ext/polars/__init__.py
magicclass/ext/polars/_viewer.py
magicclass/ext/polars/tests/__init__.py
magicclass/ext/polars/tests/test_viewer.py
magicclass/ext/pyqtgraph/__init__.py
magicclass/ext/pyqtgraph/_const.py
magicclass/ext/pyqtgraph/components.py
magicclass/ext/pyqtgraph/graph_items.py
magicclass/ext/pyqtgraph/mouse_event.py
magicclass/ext/pyqtgraph/plot_api.py
magicclass/ext/pyqtgraph/widgets.py
magicclass/ext/pyqtgraph/tests/__init__.py
magicclass/ext/pyqtgraph/tests/test_qtgraph.py
magicclass/ext/qtconsole/__init__.py
magicclass/ext/qtconsole/_qt.py
magicclass/ext/qtconsole/widgets.py
magic_class-0.7.20.dist-info/METADATA
magic_class-0.7.20.dist-info/WHEEL
magic_class-0.7.20.dist-info/licenses/LICENSE
magic_class-0.7.20.dist-info/RECORD
