Metadata-Version: 2.4
Name: magic-class
Version: 0.7.20
Summary: Generate multifunctional GUIs from classes
Project-URL: Download, https://github.com/hanjinliu/magic-class
Author-email: Hanjin Liu <liuhanjin.sc@gmail.com>
License: BSD 3-Clause License
License-File: LICENSE
Classifier: Intended Audience :: Developers
Classifier: Operating System :: OS Independent
Classifier: Programming Language :: Python
Classifier: Programming Language :: Python :: 3 :: Only
Classifier: Programming Language :: Python :: 3.9
Classifier: Programming Language :: Python :: 3.10
Classifier: Programming Language :: Python :: 3.11
Classifier: Programming Language :: Python :: 3.12
Classifier: Programming Language :: Python :: 3.13
Classifier: Programming Language :: Python :: 3.14
Requires-Python: >=3.9
Requires-Dist: docstring-parser>=0.15
Requires-Dist: macro-kit>=0.4.6
Requires-Dist: magicgui>=0.8.0
Requires-Dist: psygnal>=0.9.0
Requires-Dist: qtpy>=1.10.0
Requires-Dist: superqt[iconify]>=0.6.1
Requires-Dist: typing-extensions>=4.5.0
Provides-Extra: docs
Requires-Dist: docutils>=0.17.1; extra == 'docs'
Requires-Dist: matplotlib>=3.8.2; extra == 'docs'
Requires-Dist: mkdocs; extra == 'docs'
Requires-Dist: mkdocs-autorefs==1.0.1; extra == 'docs'
Requires-Dist: mkdocs-gen-files==0.5.0; extra == 'docs'
Requires-Dist: mkdocs-material-extensions==1.3.1; extra == 'docs'
Requires-Dist: mkdocs-material==9.5.23; extra == 'docs'
Requires-Dist: mkdocstrings-python==1.10.8; extra == 'docs'
Requires-Dist: mkdocstrings==0.25.2; extra == 'docs'
Requires-Dist: numpy; extra == 'docs'
Requires-Dist: pandas>=2.1; extra == 'docs'
Requires-Dist: pyqt5>=5.12.0; extra == 'docs'
Requires-Dist: pyqtgraph>=0.13.2; extra == 'docs'
Requires-Dist: vispy>=0.11.0; extra == 'docs'
Provides-Extra: pyqt5
Requires-Dist: pyqt5>=5.12.0; extra == 'pyqt5'
Provides-Extra: pyqt6
Requires-Dist: pyqt6; extra == 'pyqt6'
Provides-Extra: pyside2
Requires-Dist: pyside2>=5.15; (python_version >= '3.9') and extra == 'pyside2'
Provides-Extra: pyside6
Requires-Dist: pyside6; extra == 'pyside6'
Provides-Extra: testing
Requires-Dist: dask; extra == 'testing'
Requires-Dist: matplotlib>=3.8.2; extra == 'testing'
Requires-Dist: numpy; extra == 'testing'
Requires-Dist: pandas>=2.2.3; extra == 'testing'
Requires-Dist: polars>=1.12.0; extra == 'testing'
Requires-Dist: pyqtgraph>=0.13.2; extra == 'testing'
Requires-Dist: pytest; extra == 'testing'
Requires-Dist: pytest-qt; extra == 'testing'
Requires-Dist: vispy>=0.11.0; extra == 'testing'
